amigocloud/__init__.py
amigocloud/amigocloud.py
amigocloud-1.2.1.dist-info/DESCRIPTION.rst
amigocloud-1.2.1.dist-info/METADATA
amigocloud-1.2.1.dist-info/RECORD
amigocloud-1.2.1.dist-info/WHEEL
amigocloud-1.2.1.dist-info/metadata.json
amigocloud-1.2.1.dist-info/top_level.txt
