Metadata-Version: 2.0
Name: amigocloud
Version: 1.2.1
Summary: Python client for the AmigoCloud REST API
Home-page: https://github.com/amigocloud/python-amigocloud
Author: Julio M Alegria
Author-email: julio@amigocloud.com
License: MIT
Download-URL: https://github.com/amigocloud/python-amigocloud/tarball/1.2.1
Platform: UNKNOWN
Requires-Dist: requests (>=2.6.0)
Requires-Dist: six (>=1.10.0)
Requires-Dist: socketIO-client (>=0.5,<0.6)
